pydyimport/__init__.py
pydyimport/injector.py
pydyimport/pydyimport.py
pydyimport-0.0.1a3.dist-info/LICENSE
pydyimport-0.0.1a3.dist-info/METADATA
pydyimport-0.0.1a3.dist-info/WHEEL
pydyimport-0.0.1a3.dist-info/top_level.txt
pydyimport-0.0.1a3.dist-info/RECORD
