Metadata-Version: 2.1
Name: pydyimport
Version: 0.0.1a3
Summary: Dynamically import python file to aviod mess when you are using a different directory structure from python suggested.
Home-page: https://github.com/thislight/pydyimport
Author: thisLight
Author-email: l1589002388@gmail.com
License: UNKNOWN
Platform: UNKNOWN
Classifier: Programming Language :: Python :: 3
Classifier: Development Status :: 3 - Alpha
Classifier: License :: OSI Approved :: GNU General Public License v3 or later (GPLv3+)
Classifier: Operating System :: OS Independent
Classifier: Topic :: Software Development
